customer_analyzer/__init__.py
customer_analyzer/analyze.py
customer_analyzer/cli.py
customer_analyzer-0.1.0.dist-info/METADATA
customer_analyzer-0.1.0.dist-info/WHEEL
customer_analyzer-0.1.0.dist-info/entry_points.txt
customer_analyzer-0.1.0.dist-info/top_level.txt
customer_analyzer-0.1.0.dist-info/RECORD
