Metadata-Version: 2.1
Name: customer-analyzer
Version: 0.1.0
Summary: A package to analyze customer data from a CSV file and generate a detailed report
Author-email: Your Name <your-email@example.com>
License: MIT
Requires-Python: >=3.7
